plainchart/__init__.py
plainchart/plainchart.py
plainchart/styles.py
plainchart-0.2.1.dist-info/METADATA
plainchart-0.2.1.dist-info/RECORD
plainchart-0.2.1.dist-info/WHEEL
plainchart-0.2.1.dist-info/top_level.txt
