Metadata-Version: 2.1
Name: plainchart
Version: 0.2.1
Summary: A simple plain-text, no-dependencies, pip-installable, open-source charting utility in Python.
Home-page: https://github.com/gduverger/plainchart
Author: Georges Duverger
Author-email: georges.duverger@gmail.com
License: MIT
Platform: UNKNOWN
Classifier: Programming Language :: Python :: 3
Classifier: License :: OSI Approved :: MIT License
Classifier: Operating System :: OS Independent
Classifier: Intended Audience :: Developers
Classifier: Natural Language :: English
Requires-Python: >=3
